calc_rustica/__init__.py
calc_rustica/operacoes.py
calculadora_rustica-1.0.6.dist-info/DESCRIPTION.rst
calculadora_rustica-1.0.6.dist-info/METADATA
calculadora_rustica-1.0.6.dist-info/RECORD
calculadora_rustica-1.0.6.dist-info/WHEEL
calculadora_rustica-1.0.6.dist-info/metadata.json
calculadora_rustica-1.0.6.dist-info/top_level.txt
