Metadata-Version: 2.0
Name: calculadora-rustica
Version: 1.0.6
Summary: This is a project test
Home-page: https://github.com/JaineBudke/BIOME_testes_calcrustica.git
Author: Jaine Budke
Author-email: jainebudke@hotmail.com
License: MIT
Keywords: bioinformatics neuroscience teste
Platform: UNKNOWN
Classifier: Development Status :: 1 - Planning
Classifier: Intended Audience :: Developers
Classifier: Topic :: Software Development :: Build Tools
Classifier: Intended Audience :: Science/Research
Classifier: Topic :: Scientific/Engineering :: Bio-Informatics
Classifier: License :: OSI Approved :: Academic Free License (AFL)
Classifier: Programming Language :: Python
Classifier: Programming Language :: Python :: 3
Requires-Dist: numpy (>=1.12)
Requires-Dist: scipy (>=0.19)
Requires-Dist: sh (>=1.11)
